mf_algorithms/__init__.py
mf_algorithms/example.py
mf_algorithms/functions.py
mf_algorithms-0.2.2.dist-info/LICENSE
mf_algorithms-0.2.2.dist-info/METADATA
mf_algorithms-0.2.2.dist-info/WHEEL
mf_algorithms-0.2.2.dist-info/top_level.txt
mf_algorithms-0.2.2.dist-info/RECORD
