Metadata-Version: 2.1
Name: mf-algorithms
Version: 0.2.2
Summary: MF Algorithms contains various matrix factorization methods utilizing different iterative update rules.
Home-page: https://github.com/chaue/mf-algorithms
Author: Edwin Chau
Author-email: edwinchau@ucla.edu
License: MIT
Keywords: mf_algorithms
Platform: UNKNOWN
Classifier: Development Status :: 2 - Pre-Alpha
Classifier: Intended Audience :: Science/Research 
Classifier: License :: OSI Approved :: MIT License
Classifier: Natural Language :: English
Classifier: Programming Language :: Python
Classifier: Programming Language :: Python :: 3
Classifier: Programming Language :: Python :: 3 :: Only
Classifier: Programming Language :: Python :: 3.6
Classifier: Programming Language :: Python :: 3.7
Classifier: Programming Language :: Python :: 3.8
Classifier: Topic :: Scientific/Engineering
Requires-Python: >=3.6
Requires-Dist: numpy
Provides-Extra: all
Requires-Dist: numpy ; extra == 'all'
Requires-Dist: pytest ; extra == 'all'
Requires-Dist: bump2version (>=1.0.0) ; extra == 'all'
Requires-Dist: ipython (>=7.5.0) ; extra == 'all'
Requires-Dist: twine (>=1.13.0) ; extra == 'all'
Requires-Dist: wheel (>=0.33.1) ; extra == 'all'
Requires-Dist: tox (>=3.15.0) ; extra == 'all'
Provides-Extra: dev
Requires-Dist: pytest ; extra == 'dev'
Requires-Dist: bump2version (>=1.0.0) ; extra == 'dev'
Requires-Dist: ipython (>=7.5.0) ; extra == 'dev'
Requires-Dist: twine (>=1.13.0) ; extra == 'dev'
Requires-Dist: wheel (>=0.33.1) ; extra == 'dev'
Requires-Dist: tox (>=3.15.0) ; extra == 'dev'
Provides-Extra: docs
Provides-Extra: setup
Provides-Extra: test
Requires-Dist: pytest ; extra == 'test'
